classifier_anshp/__init__.py
classifier_anshp/main.py
classifier_linear/__init__.py
classifier_linear/main.py
classifier_anshp-0.30.9.dist-info/METADATA
classifier_anshp-0.30.9.dist-info/WHEEL
classifier_anshp-0.30.9.dist-info/entry_points.txt
classifier_anshp-0.30.9.dist-info/license.txt
classifier_anshp-0.30.9.dist-info/top_level.txt
classifier_anshp-0.30.9.dist-info/RECORD
