Metadata-Version: 2.1
Name: classifier-anshp
Version: 0.30.9
Summary: A linear classifier built using tensorflow.
Home-page: https://github.com/ANSHPG/pypi-pkg-clsfr
Author: Anshuman Pattnaik
Author-email: helloanshu04@gmail.com
Classifier: Programming Language :: Python :: 3
Classifier: License :: OSI Approved :: MIT License
Classifier: Operating System :: OS Independent
Requires-Python: >=3.6
License-File: license.txt
Requires-Dist: tensorflow>=2.0.0
Requires-Dist: numpy>=1.18.0
